{
	"В лепёшке": "[{\"title\":\"Добавки\",\"type\":\"many_many\",\"required\":false,\"custom\":false,\"options\":[{\"id\":2,\"name\":\"Маринованный огурчик\",\"prices\":[{\"price\":\"250000\",\"price_formatted\":\"25 ₽\",\"size\":\"40\",\"size_formatted\":\"40 г\"}],\"price\":\"250000\",\"price_formatted\":\"25 ₽\",\"photo\":\"https:\\/\\/cdn.foodpicasso.com\\/assets\\/2022\\/07\\/26\\/3027c57c6ff755a36a23f7279b0a9630---jpg_160x160_b3903_convert.jpg\",\"photoPart\":\"https:\\/\\/cdn.foodpicasso.com\\/assets\\/2022\\/07\\/26\\/3027c57c6ff755a36a23f7279b0a9630---jpg_375x375:whitepadding15_9edf7_convert.jpg\",\"size\":\"40\",\"size_formatted\":\"40 г\",\"min\":0,\"max\":0},{\"id\":3,\"name\":\"Свежий огурчик\",\"prices\":[{\"price\":\"230000\",\"price_formatted\":\"23 ₽\",\"size\":\"40\",\"size_formatted\":\"40 г\"}],\"price\":\"230000\",\"price_formatted\":\"23 ₽\",\"photo\":\"https:\\/\\/cdn.foodpicasso.com\\/assets\\/2022\\/07\\/26\\/f31b632903ee3d0e6249289f618eb247---png_160x160_b3903_convert.png\",\"photoPart\":\"https:\\/\\/cdn.foodpicasso.com\\/assets\\/2022\\/07\\/26\\/f31b632903ee3d0e6249289f618eb247---png_375x375:whitepadding15_9edf7_convert.png\",\"size\":\"40\",\"size_formatted\":\"40 г\",\"min\":0,\"max\":0},{\"id\":4,\"name\":\"Лучок маринованный\",\"prices\":[{\"price\":\"100000\",\"price_formatted\":\"10 ₽\",\"size\":\"15\",\"size_formatted\":\"15 г\"}],\"price\":\"100000\",\"price_formatted\":\"10 ₽\",\"photo\":\"https:\\/\\/cdn.foodpicasso.com\\/assets\\/2022\\/07\\/26\\/6d1aab5de9b6f247f9afac3ee819846d---jpg_160x160_b3903_convert.jpg\",\"photoPart\":\"https:\\/\\/cdn.foodpicasso.com\\/assets\\/2022\\/07\\/26\\/6d1aab5de9b6f247f9afac3ee819846d---jpg_375x375:whitepadding15_9edf7_convert.jpg\",\"size\":\"15\",\"size_formatted\":\"15 г\",\"min\":0,\"max\":0},{\"id\":6,\"name\":\"Грибочки маринованные\",\"prices\":[{\"price\":\"770000\",\"price_formatted\":\"77 ₽\",\"size\":\"40\",\"size_formatted\":\"40 г\"}],\"price\":\"770000\",\"price_formatted\":\"77 ₽\",\"photo\":\"https:\\/\\/cdn.foodpicasso.com\\/assets\\/2022\\/07\\/26\\/5242c27b01fd320ea21196c89f7f4e39---jpg_160x160_b3903_convert.jpg\",\"photoPart\":\"https:\\/\\/cdn.foodpicasso.com\\/assets\\/2022\\/07\\/26\\/5242c27b01fd320ea21196c89f7f4e39---jpg_375x375:whitepadding15_9edf7_convert.jpg\",\"size\":\"40\",\"size_formatted\":\"40 г\",\"min\":0,\"max\":0},{\"id\":7,\"name\":\"Перчик болгарский\",\"prices\":[{\"price\":\"350000\",\"price_formatted\":\"35 ₽\",\"size\":\"15\",\"size_formatted\":\"15 г\"}],\"price\":\"350000\",\"price_formatted\":\"35 ₽\",\"photo\":\"https:\\/\\/cdn.foodpicasso.com\\/assets\\/2022\\/07\\/26\\/e024751115d70ea661433d0d73c1a659---jpg_160x160_b3903_convert.jpg\",\"photoPart\":\"https:\\/\\/cdn.foodpicasso.com\\/assets\\/2022\\/07\\/26\\/e024751115d70ea661433d0d73c1a659---jpg_375x375:whitepadding15_9edf7_convert.jpg\",\"size\":\"15\",\"size_formatted\":\"15 г\",\"min\":0,\"max\":0},{\"id\":9,\"name\":\"Томат\",\"prices\":[{\"price\":\"250000\",\"price_formatted\":\"25 ₽\",\"size\":\"40\",\"size_formatted\":\"40 г\"}],\"price\":\"250000\",\"price_formatted\":\"25 ₽\",\"photo\":\"https:\\/\\/cdn.foodpicasso.com\\/assets\\/2022\\/07\\/26\\/c7a108c28e3bb41dac5a8549386f89b5---jpeg_160x160_b3903_convert.jpeg\",\"photoPart\":\"https:\\/\\/cdn.foodpicasso.com\\/assets\\/2022\\/07\\/26\\/c7a108c28e3bb41dac5a8549386f89b5---jpeg_375x375:whitepadding15_9edf7_convert.jpeg\",\"size\":\"40\",\"size_formatted\":\"40 г\",\"min\":0,\"max\":0},{\"id\":11,\"name\":\"Бекон\",\"prices\":[{\"price\":\"730000\",\"price_formatted\":\"73 ₽\",\"size\":\"40\",\"size_formatted\":\"40 г\"}],\"price\":\"730000\",\"price_formatted\":\"73 ₽\",\"photo\":\"https:\\/\\/cdn.foodpicasso.com\\/assets\\/2022\\/07\\/26\\/f5be1451d119eb263739e675853d89c4---jpeg_160x160_b3903_convert.jpeg\",\"photoPart\":\"https:\\/\\/cdn.foodpicasso.com\\/assets\\/2022\\/07\\/26\\/f5be1451d119eb263739e675853d89c4---jpeg_375x375:whitepadding15_9edf7_convert.jpeg\",\"size\":\"40\",\"size_formatted\":\"40 г\",\"min\":0,\"max\":0},{\"id\":12,\"name\":\"Оливки\",\"prices\":[{\"price\":\"370000\",\"price_formatted\":\"37 ₽\",\"size\":\"15\",\"size_formatted\":\"15 г\"}],\"price\":\"370000\",\"price_formatted\":\"37 ₽\",\"photo\":\"https:\\/\\/cdn.foodpicasso.com\\/assets\\/2022\\/07\\/26\\/9e2c97a6a624aa46a29c914b8ddff5a2---jpg_160x160_b3903_convert.jpg\",\"photoPart\":\"https:\\/\\/cdn.foodpicasso.com\\/assets\\/2022\\/07\\/26\\/9e2c97a6a624aa46a29c914b8ddff5a2---jpg_375x375:whitepadding15_9edf7_convert.jpg\",\"size\":\"15\",\"size_formatted\":\"15 г\",\"min\":0,\"max\":0},{\"id\":13,\"name\":\"Сыр\",\"prices\":[{\"price\":\"170000\",\"price_formatted\":\"17 ₽\",\"size\":\"15\",\"size_formatted\":\"15 г\"}],\"price\":\"170000\",\"price_formatted\":\"17 ₽\",\"photo\":\"https:\\/\\/cdn.foodpicasso.com\\/assets\\/2022\\/07\\/26\\/6ffb36fd8791beee98410f7d04fce6f5---jpg_160x160_b3903_convert.jpg\",\"photoPart\":\"https:\\/\\/cdn.foodpicasso.com\\/assets\\/2022\\/07\\/26\\/6ffb36fd8791beee98410f7d04fce6f5---jpg_375x375:whitepadding15_9edf7_convert.jpg\",\"size\":\"15\",\"size_formatted\":\"15 г\",\"min\":0,\"max\":0},{\"id\":14,\"name\":\"Горчица\",\"prices\":[{\"price\":\"100000\",\"price_formatted\":\"10 ₽\"}],\"price\":\"100000\",\"price_formatted\":\"10 ₽\",\"photo\":\"https:\\/\\/cdn.foodpicasso.com\\/assets\\/2022\\/07\\/26\\/d47473bd814449044c0dcf34983c9040---png_160x160_b3903_convert.png\",\"photoPart\":\"https:\\/\\/cdn.foodpicasso.com\\/assets\\/2022\\/07\\/26\\/d47473bd814449044c0dcf34983c9040---png_375x375:whitepadding15_9edf7_convert.png\",\"size\":\"\",\"size_formatted\":\"\",\"min\":0,\"max\":0},{\"id\":15,\"name\":\"Яйцо\",\"prices\":[{\"price\":\"250000\",\"price_formatted\":\"25 ₽\",\"size\":\"20\",\"size_formatted\":\"20 г\"}],\"price\":\"250000\",\"price_formatted\":\"25 ₽\",\"photo\":\"https:\\/\\/cdn.foodpicasso.com\\/assets\\/2022\\/07\\/26\\/592fe930494dd2d25e5756e72a3b0d2f---jpg_160x160_b3903_convert.jpg\",\"photoPart\":\"https:\\/\\/cdn.foodpicasso.com\\/assets\\/2022\\/07\\/26\\/592fe930494dd2d25e5756e72a3b0d2f---jpg_375x375:whitepadding15_9edf7_convert.jpg\",\"size\":\"20\",\"size_formatted\":\"20 г\",\"min\":0,\"max\":0},{\"id\":79,\"name\":\"Куриное филе\",\"prices\":[{\"price\":\"550000\",\"price_formatted\":\"55 ₽\",\"size\":\"80\",\"size_formatted\":\"80 г\"}],\"price\":\"550000\",\"price_formatted\":\"55 ₽\",\"photo\":\"https:\\/\\/cdn.foodpicasso.com\\/assets\\/2022\\/07\\/26\\/1eff1d6650d328e0e975fd6a3c4ffdf7---jpg_160x160_b3903_convert.jpg\",\"photoPart\":\"https:\\/\\/cdn.foodpicasso.com\\/assets\\/2022\\/07\\/26\\/1eff1d6650d328e0e975fd6a3c4ffdf7---jpg_375x375:whitepadding15_9edf7_convert.jpg\",\"size\":\"80\",\"size_formatted\":\"80 г\",\"min\":0,\"max\":0},{\"id\":80,\"name\":\"Сосиска\",\"prices\":[{\"price\":\"780000\",\"price_formatted\":\"78 ₽\",\"size\":\"100\",\"size_formatted\":\"100 г\"}],\"price\":\"780000\",\"price_formatted\":\"78 ₽\",\"photo\":\"https:\\/\\/cdn.foodpicasso.com\\/assets\\/2022\\/07\\/26\\/5f59c9ea34222ee24a45dd57dab89e3e---jpeg_160x160_b3903_convert.jpeg\",\"photoPart\":\"https:\\/\\/cdn.foodpicasso.com\\/assets\\/2022\\/07\\/26\\/5f59c9ea34222ee24a45dd57dab89e3e---jpeg_375x375:whitepadding15_9edf7_convert.jpeg\",\"size\":\"100\",\"size_formatted\":\"100 г\",\"min\":0,\"max\":0},{\"id\":93,\"name\":\"Рубленый бифштекс из говядины\",\"prices\":[{\"price\":\"730000\",\"price_formatted\":\"73 ₽\",\"size\":\"80\",\"size_formatted\":\"80 г\"}],\"price\":\"730000\",\"price_formatted\":\"73 ₽\",\"photo\":\"https:\\/\\/cdn.foodpicasso.com\\/assets\\/2022\\/07\\/27\\/cd8bab043d870f9b582393d1bcf8c502---jpg_160x160_b3903_convert.jpg\",\"photoPart\":\"https:\\/\\/cdn.foodpicasso.com\\/assets\\/2022\\/07\\/27\\/cd8bab043d870f9b582393d1bcf8c502---jpg_375x375:whitepadding15_9edf7_convert.jpg\",\"size\":\"80\",\"size_formatted\":\"80 г\",\"min\":0,\"max\":0},{\"id\":94,\"name\":\"Куриное филе в панировке\",\"prices\":[{\"price\":\"550000\",\"price_formatted\":\"55 ₽\",\"size\":\"80\",\"size_formatted\":\"80 г\"}],\"price\":\"550000\",\"price_formatted\":\"55 ₽\",\"photo\":\"https:\\/\\/cdn.foodpicasso.com\\/assets\\/2022\\/07\\/27\\/47e053e1ee0cdce8889d017874467726---jpg_160x160_b3903_convert.jpg\",\"photoPart\":\"https:\\/\\/cdn.foodpicasso.com\\/assets\\/2022\\/07\\/27\\/47e053e1ee0cdce8889d017874467726---jpg_375x375:whitepadding15_9edf7_convert.jpg\",\"size\":\"80\",\"size_formatted\":\"80 г\",\"min\":0,\"max\":0},{\"id\":95,\"name\":\"Лист салата\",\"prices\":[{\"price\":\"100000\",\"price_formatted\":\"10 ₽\",\"size\":\"10\",\"size_formatted\":\"10 г\"}],\"price\":\"100000\",\"price_formatted\":\"10 ₽\",\"photo\":\"https:\\/\\/cdn.foodpicasso.com\\/assets\\/2022\\/07\\/27\\/89184e3f5ac28a020a528552b2675b40---jpg_160x160_b3903_convert.jpg\",\"photoPart\":\"https:\\/\\/cdn.foodpicasso.com\\/assets\\/2022\\/07\\/27\\/89184e3f5ac28a020a528552b2675b40---jpg_375x375:whitepadding15_9edf7_convert.jpg\",\"size\":\"10\",\"size_formatted\":\"10 г\",\"min\":0,\"max\":0},{\"id\":96,\"name\":\"Фри\",\"prices\":[{\"price\":\"380000\",\"price_formatted\":\"38 ₽\",\"size\":\"75\",\"size_formatted\":\"75 г\"}],\"price\":\"380000\",\"price_formatted\":\"38 ₽\",\"photo\":\"https:\\/\\/cdn.foodpicasso.com\\/assets\\/2022\\/07\\/27\\/11ac767ce3f35ee9a208a2ea1b132580---jpeg_160x160_b3903_convert.jpeg\",\"photoPart\":\"https:\\/\\/cdn.foodpicasso.com\\/assets\\/2022\\/07\\/27\\/11ac767ce3f35ee9a208a2ea1b132580---jpeg_375x375:whitepadding15_9edf7_convert.jpeg\",\"size\":\"75\",\"size_formatted\":\"75 г\",\"min\":0,\"max\":0}],\"quarterType\":\"\",\"min\":0,\"max\":0},{\"title\":\"Сделай вкуснее\",\"type\":\"many_many\",\"required\":true,\"custom\":false,\"options\":[{\"id\":47,\"name\":\"Маринованный лучок\",\"prices\":[{\"price\":0,\"price_formatted\":\"0 ₽\"}],\"price\":0,\"price_formatted\":\"0 ₽\",\"photo\":\"https:\\/\\/cdn.foodpicasso.com\\/assets\\/2022\\/07\\/26\\/4fcd48fe7acb9ff3ba358d215562f8c3---jpg_160x160_b3903_convert.jpg\",\"photoPart\":\"https:\\/\\/cdn.foodpicasso.com\\/assets\\/2022\\/07\\/26\\/4fcd48fe7acb9ff3ba358d215562f8c3---jpg_375x375:whitepadding15_9edf7_convert.jpg\",\"size\":\"\",\"size_formatted\":\"\",\"min\":0,\"max\":0},{\"id\":48,\"name\":\"Горчица\",\"prices\":[{\"price\":0,\"price_formatted\":\"0 ₽\"}],\"price\":0,\"price_formatted\":\"0 ₽\",\"photo\":\"https:\\/\\/cdn.foodpicasso.com\\/assets\\/2022\\/07\\/26\\/9c74acfe562dab9859eddc026f9b4619---png_160x160_b3903_convert.png\",\"photoPart\":\"https:\\/\\/cdn.foodpicasso.com\\/assets\\/2022\\/07\\/26\\/9c74acfe562dab9859eddc026f9b4619---png_375x375:whitepadding15_9edf7_convert.png\",\"size\":\"\",\"size_formatted\":\"\",\"min\":0,\"max\":0},{\"id\":127,\"name\":\"Без лука\",\"prices\":[{\"price\":0,\"price_formatted\":\"0 ₽\"}],\"price\":0,\"price_formatted\":\"0 ₽\",\"photo\":\"https:\\/\\/cdn.foodpicasso.com\\/assets\\/2022\\/07\\/26\\/ffc79de2a3b4372f4db880060cb3713a---jpg_160x160_b3903_convert.jpg\",\"photoPart\":\"https:\\/\\/cdn.foodpicasso.com\\/assets\\/2022\\/07\\/26\\/ffc79de2a3b4372f4db880060cb3713a---jpg_375x375:whitepadding15_9edf7_convert.jpg\",\"size\":\"\",\"size_formatted\":\"\",\"min\":0,\"max\":0},{\"id\":128,\"name\":\"Без горчицы\",\"prices\":[{\"price\":0,\"price_formatted\":\"0 ₽\"}],\"price\":0,\"price_formatted\":\"0 ₽\",\"photo\":\"https:\\/\\/cdn.foodpicasso.com\\/assets\\/2022\\/07\\/26\\/01cfe1883bb4409a76de5c7b3e341cde---jpg_160x160_b3903_convert.jpg\",\"photoPart\":\"https:\\/\\/cdn.foodpicasso.com\\/assets\\/2022\\/07\\/26\\/01cfe1883bb4409a76de5c7b3e341cde---jpg_375x375:whitepadding15_9edf7_convert.jpg\",\"size\":\"\",\"size_formatted\":\"\",\"min\":0,\"max\":0},{\"id\":126,\"name\":\"Без горчицы и лука\",\"prices\":[{\"price\":0,\"price_formatted\":\"0 ₽\"}],\"price\":0,\"price_formatted\":\"0 ₽\",\"photo\":\"https:\\/\\/cdn.foodpicasso.com\\/assets\\/2022\\/07\\/26\\/f3018ad3bb3a188a2663898613be7193---jpg_160x160_b3903_convert.jpg\",\"photoPart\":\"https:\\/\\/cdn.foodpicasso.com\\/assets\\/2022\\/07\\/26\\/f3018ad3bb3a188a2663898613be7193---jpg_375x375:whitepadding15_9edf7_convert.jpg\",\"size\":\"\",\"size_formatted\":\"\",\"min\":0,\"max\":0}],\"quarterType\":\"\",\"min\":0,\"max\":0},{\"title\":\"Картофель\",\"type\":\"many_many\",\"required\":false,\"custom\":false,\"options\":[{\"id\":129,\"name\":\"Картофель фри\",\"prices\":[{\"price\":\"1100000\",\"price_formatted\":\"110 ₽\",\"size\":\"150\",\"size_formatted\":\"150 г\"},{\"price\":\"1320000\",\"price_formatted\":\"132 ₽\",\"size\":\"200\",\"size_formatted\":\"200 г\"},{\"price\":\"1670000\",\"price_formatted\":\"167 ₽\",\"size\":\"250\",\"size_formatted\":\"250 г\"},{\"price\":\"2110000\",\"price_formatted\":\"211 ₽\",\"size\":\"350\",\"size_formatted\":\"350 г\"}],\"price\":\"1100000\",\"price_formatted\":\"110 ₽\",\"photo\":\"https:\\/\\/cdn.foodpicasso.com\\/assets\\/2022\\/07\\/27\\/631587a0ccee9ed05aa0b57814fe2eaf---jpeg_160x160_b3903_convert.jpeg\",\"photoPart\":\"https:\\/\\/cdn.foodpicasso.com\\/assets\\/2022\\/07\\/27\\/631587a0ccee9ed05aa0b57814fe2eaf---jpeg_375x375:whitepadding15_9edf7_convert.jpeg\",\"size\":\"150\",\"size_formatted\":\"150 г\",\"min\":0,\"max\":0},{\"id\":130,\"name\":\"Картофельные дольки от Папы\",\"prices\":[{\"price\":\"1680000\",\"price_formatted\":\"168 ₽\",\"size\":\"200\",\"size_formatted\":\"200 г\"}],\"price\":\"1680000\",\"price_formatted\":\"168 ₽\",\"photo\":\"https:\\/\\/cdn.foodpicasso.com\\/assets\\/2022\\/07\\/27\\/8f6d261e746716979ef977c75dc286f6---jpg_160x160_b3903_convert.jpg\",\"photoPart\":\"https:\\/\\/cdn.foodpicasso.com\\/assets\\/2022\\/07\\/27\\/8f6d261e746716979ef977c75dc286f6---jpg_375x375:whitepadding15_9edf7_convert.jpg\",\"size\":\"200\",\"size_formatted\":\"200 г\",\"min\":0,\"max\":0},{\"id\":131,\"name\":\"Картофельные дольки от Папы СО СПЕЦИЯМИ\",\"prices\":[{\"price\":\"1680000\",\"price_formatted\":\"168 ₽\",\"size\":\"200\",\"size_formatted\":\"200 г\"}],\"price\":\"1680000\",\"price_formatted\":\"168 ₽\",\"photo\":\"https:\\/\\/cdn.foodpicasso.com\\/assets\\/2022\\/07\\/27\\/0794679dc8d1d64ebefb3273af8039c8---jpg_160x160_b3903_convert.jpg\",\"photoPart\":\"https:\\/\\/cdn.foodpicasso.com\\/assets\\/2022\\/07\\/27\\/0794679dc8d1d64ebefb3273af8039c8---jpg_375x375:whitepadding15_9edf7_convert.jpg\",\"size\":\"200\",\"size_formatted\":\"200 г\",\"min\":0,\"max\":0}],\"quarterType\":\"\",\"min\":0,\"max\":0},{\"title\":\"Соусы\",\"type\":\"many_many\",\"required\":false,\"custom\":false,\"options\":[{\"id\":132,\"name\":\"Без соуса\",\"prices\":[{\"price\":0,\"price_formatted\":\"0 ₽\"}],\"price\":0,\"price_formatted\":\"0 ₽\",\"photo\":\"https:\\/\\/cdn.foodpicasso.com\\/assets\\/2022\\/07\\/26\\/04d2913ea263586c8509e46b847afeea---jpg_160x160_b3903_convert.jpg\",\"photoPart\":\"https:\\/\\/cdn.foodpicasso.com\\/assets\\/2022\\/07\\/26\\/04d2913ea263586c8509e46b847afeea---jpg_375x375:whitepadding15_9edf7_convert.jpg\",\"size\":\"\",\"size_formatted\":\"\",\"min\":0,\"max\":0},{\"id\":49,\"name\":\"Томатный кетчуп\",\"prices\":[{\"price\":\"260000\",\"price_formatted\":\"26 ₽\",\"size\":\"40\",\"size_formatted\":\"40 г\"}],\"price\":\"260000\",\"price_formatted\":\"26 ₽\",\"photo\":\"https:\\/\\/cdn.foodpicasso.com\\/assets\\/2022\\/07\\/26\\/601e403d7e68b5ad04e69dce1417531c---jpg_160x160_b3903_convert.jpg\",\"photoPart\":\"https:\\/\\/cdn.foodpicasso.com\\/assets\\/2022\\/07\\/26\\/601e403d7e68b5ad04e69dce1417531c---jpg_375x375:whitepadding15_9edf7_convert.jpg\",\"size\":\"40\",\"size_formatted\":\"40 г\",\"min\":0,\"max\":0},{\"id\":50,\"name\":\"Соус Чили\",\"prices\":[{\"price\":\"430000\",\"price_formatted\":\"43 ₽\",\"size\":\"40\",\"size_formatted\":\"40 г\"}],\"price\":\"430000\",\"price_formatted\":\"43 ₽\",\"photo\":\"https:\\/\\/cdn.foodpicasso.com\\/assets\\/2022\\/07\\/26\\/eef4285ac6e066ab335d70dc2f5b77ee---png_160x160_b3903_convert.png\",\"photoPart\":\"https:\\/\\/cdn.foodpicasso.com\\/assets\\/2022\\/07\\/26\\/eef4285ac6e066ab335d70dc2f5b77ee---png_375x375:whitepadding15_9edf7_convert.png\",\"size\":\"40\",\"size_formatted\":\"40 г\",\"min\":0,\"max\":0},{\"id\":51,\"name\":\"Тайский соус\",\"prices\":[{\"price\":\"520000\",\"price_formatted\":\"52 ₽\",\"size\":\"40\",\"size_formatted\":\"40 г\"}],\"price\":\"520000\",\"price_formatted\":\"52 ₽\",\"photo\":\"https:\\/\\/cdn.foodpicasso.com\\/assets\\/2022\\/07\\/26\\/6a2e0699ef258c25dfa062aadc6c90dc---jpg_160x160_b3903_convert.jpg\",\"photoPart\":\"https:\\/\\/cdn.foodpicasso.com\\/assets\\/2022\\/07\\/26\\/6a2e0699ef258c25dfa062aadc6c90dc---jpg_375x375:whitepadding15_9edf7_convert.jpg\",\"size\":\"40\",\"size_formatted\":\"40 г\",\"min\":0,\"max\":0},{\"id\":52,\"name\":\"Фирменный соус\",\"prices\":[{\"price\":\"200000\",\"price_formatted\":\"20 ₽\",\"size\":\"40\",\"size_formatted\":\"40 г\"}],\"price\":\"200000\",\"price_formatted\":\"20 ₽\",\"photo\":\"https:\\/\\/cdn.foodpicasso.com\\/assets\\/2022\\/07\\/26\\/fc667b4ca67a4128810d147f84afde36---jpg_160x160_b3903_convert.jpg\",\"photoPart\":\"https:\\/\\/cdn.foodpicasso.com\\/assets\\/2022\\/07\\/26\\/fc667b4ca67a4128810d147f84afde36---jpg_375x375:whitepadding15_9edf7_convert.jpg\",\"size\":\"40\",\"size_formatted\":\"40 г\",\"min\":0,\"max\":0},{\"id\":53,\"name\":\"Сырный соус\",\"prices\":[{\"price\":\"440000\",\"price_formatted\":\"44 ₽\",\"size\":\"40\",\"size_formatted\":\"40 г\"}],\"price\":\"440000\",\"price_formatted\":\"44 ₽\",\"photo\":\"https:\\/\\/cdn.foodpicasso.com\\/assets\\/2022\\/07\\/26\\/715265820b430c651910f6304c86642c---jpg_160x160_b3903_convert.jpg\",\"photoPart\":\"https:\\/\\/cdn.foodpicasso.com\\/assets\\/2022\\/07\\/26\\/715265820b430c651910f6304c86642c---jpg_375x375:whitepadding15_9edf7_convert.jpg\",\"size\":\"40\",\"size_formatted\":\"40 г\",\"min\":0,\"max\":0},{\"id\":54,\"name\":\"Барбекю по-техасски\",\"prices\":[{\"price\":\"500000\",\"price_formatted\":\"50 ₽\",\"size\":\"40\",\"size_formatted\":\"40 г\"}],\"price\":\"500000\",\"price_formatted\":\"50 ₽\",\"photo\":\"https:\\/\\/cdn.foodpicasso.com\\/assets\\/2022\\/07\\/26\\/42dfc0ce7d54d72c62f16fcc95926894---jpg_160x160_b3903_convert.jpg\",\"photoPart\":\"https:\\/\\/cdn.foodpicasso.com\\/assets\\/2022\\/07\\/26\\/42dfc0ce7d54d72c62f16fcc95926894---jpg_375x375:whitepadding15_9edf7_convert.jpg\",\"size\":\"40\",\"size_formatted\":\"40 г\",\"min\":0,\"max\":0}],\"quarterType\":\"\",\"min\":0,\"max\":0}]",
	"Бургеры": "[{\"title\":\"Добавки\",\"type\":\"many_many\",\"required\":false,\"custom\":false,\"options\":[{\"id\":2,\"name\":\"Маринованный огурчик\",\"prices\":[{\"price\":\"250000\",\"price_formatted\":\"25 ₽\",\"size\":\"40\",\"size_formatted\":\"40 г\"}],\"price\":\"250000\",\"price_formatted\":\"25 ₽\",\"photo\":\"https:\\/\\/cdn.foodpicasso.com\\/assets\\/2022\\/07\\/26\\/3027c57c6ff755a36a23f7279b0a9630---jpg_160x160_b3903_convert.jpg\",\"photoPart\":\"https:\\/\\/cdn.foodpicasso.com\\/assets\\/2022\\/07\\/26\\/3027c57c6ff755a36a23f7279b0a9630---jpg_375x375:whitepadding15_9edf7_convert.jpg\",\"size\":\"40\",\"size_formatted\":\"40 г\",\"min\":0,\"max\":0},{\"id\":3,\"name\":\"Свежий огурчик\",\"prices\":[{\"price\":\"230000\",\"price_formatted\":\"23 ₽\",\"size\":\"40\",\"size_formatted\":\"40 г\"}],\"price\":\"230000\",\"price_formatted\":\"23 ₽\",\"photo\":\"https:\\/\\/cdn.foodpicasso.com\\/assets\\/2022\\/07\\/26\\/f31b632903ee3d0e6249289f618eb247---png_160x160_b3903_convert.png\",\"photoPart\":\"https:\\/\\/cdn.foodpicasso.com\\/assets\\/2022\\/07\\/26\\/f31b632903ee3d0e6249289f618eb247---png_375x375:whitepadding15_9edf7_convert.png\",\"size\":\"40\",\"size_formatted\":\"40 г\",\"min\":0,\"max\":0},{\"id\":4,\"name\":\"Лучок маринованный\",\"prices\":[{\"price\":\"100000\",\"price_formatted\":\"10 ₽\",\"size\":\"15\",\"size_formatted\":\"15 г\"}],\"price\":\"100000\",\"price_formatted\":\"10 ₽\",\"photo\":\"https:\\/\\/cdn.foodpicasso.com\\/assets\\/2022\\/07\\/26\\/6d1aab5de9b6f247f9afac3ee819846d---jpg_160x160_b3903_convert.jpg\",\"photoPart\":\"https:\\/\\/cdn.foodpicasso.com\\/assets\\/2022\\/07\\/26\\/6d1aab5de9b6f247f9afac3ee819846d---jpg_375x375:whitepadding15_9edf7_convert.jpg\",\"size\":\"15\",\"size_formatted\":\"15 г\",\"min\":0,\"max\":0},{\"id\":6,\"name\":\"Грибочки маринованные\",\"prices\":[{\"price\":\"770000\",\"price_formatted\":\"77 ₽\",\"size\":\"40\",\"size_formatted\":\"40 г\"}],\"price\":\"770000\",\"price_formatted\":\"77 ₽\",\"photo\":\"https:\\/\\/cdn.foodpicasso.com\\/assets\\/2022\\/07\\/26\\/5242c27b01fd320ea21196c89f7f4e39---jpg_160x160_b3903_convert.jpg\",\"photoPart\":\"https:\\/\\/cdn.foodpicasso.com\\/assets\\/2022\\/07\\/26\\/5242c27b01fd320ea21196c89f7f4e39---jpg_375x375:whitepadding15_9edf7_convert.jpg\",\"size\":\"40\",\"size_formatted\":\"40 г\",\"min\":0,\"max\":0},{\"id\":7,\"name\":\"Перчик болгарский\",\"prices\":[{\"price\":\"350000\",\"price_formatted\":\"35 ₽\",\"size\":\"15\",\"size_formatted\":\"15 г\"}],\"price\":\"350000\",\"price_formatted\":\"35 ₽\",\"photo\":\"https:\\/\\/cdn.foodpicasso.com\\/assets\\/2022\\/07\\/26\\/e024751115d70ea661433d0d73c1a659---jpg_160x160_b3903_convert.jpg\",\"photoPart\":\"https:\\/\\/cdn.foodpicasso.com\\/assets\\/2022\\/07\\/26\\/e024751115d70ea661433d0d73c1a659---jpg_375x375:whitepadding15_9edf7_convert.jpg\",\"size\":\"15\",\"size_formatted\":\"15 г\",\"min\":0,\"max\":0},{\"id\":9,\"name\":\"Томат\",\"prices\":[{\"price\":\"250000\",\"price_formatted\":\"25 ₽\",\"size\":\"40\",\"size_formatted\":\"40 г\"}],\"price\":\"250000\",\"price_formatted\":\"25 ₽\",\"photo\":\"https:\\/\\/cdn.foodpicasso.com\\/assets\\/2022\\/07\\/26\\/c7a108c28e3bb41dac5a8549386f89b5---jpeg_160x160_b3903_convert.jpeg\",\"photoPart\":\"https:\\/\\/cdn.foodpicasso.com\\/assets\\/2022\\/07\\/26\\/c7a108c28e3bb41dac5a8549386f89b5---jpeg_375x375:whitepadding15_9edf7_convert.jpeg\",\"size\":\"40\",\"size_formatted\":\"40 г\",\"min\":0,\"max\":0},{\"id\":11,\"name\":\"Бекон\",\"prices\":[{\"price\":\"730000\",\"price_formatted\":\"73 ₽\",\"size\":\"40\",\"size_formatted\":\"40 г\"}],\"price\":\"730000\",\"price_formatted\":\"73 ₽\",\"photo\":\"https:\\/\\/cdn.foodpicasso.com\\/assets\\/2022\\/07\\/26\\/f5be1451d119eb263739e675853d89c4---jpeg_160x160_b3903_convert.jpeg\",\"photoPart\":\"https:\\/\\/cdn.foodpicasso.com\\/assets\\/2022\\/07\\/26\\/f5be1451d119eb263739e675853d89c4---jpeg_375x375:whitepadding15_9edf7_convert.jpeg\",\"size\":\"40\",\"size_formatted\":\"40 г\",\"min\":0,\"max\":0},{\"id\":12,\"name\":\"Оливки\",\"prices\":[{\"price\":\"370000\",\"price_formatted\":\"37 ₽\",\"size\":\"15\",\"size_formatted\":\"15 г\"}],\"price\":\"370000\",\"price_formatted\":\"37 ₽\",\"photo\":\"https:\\/\\/cdn.foodpicasso.com\\/assets\\/2022\\/07\\/26\\/9e2c97a6a624aa46a29c914b8ddff5a2---jpg_160x160_b3903_convert.jpg\",\"photoPart\":\"https:\\/\\/cdn.foodpicasso.com\\/assets\\/2022\\/07\\/26\\/9e2c97a6a624aa46a29c914b8ddff5a2---jpg_375x375:whitepadding15_9edf7_convert.jpg\",\"size\":\"15\",\"size_formatted\":\"15 г\",\"min\":0,\"max\":0},{\"id\":13,\"name\":\"Сыр\",\"prices\":[{\"price\":\"170000\",\"price_formatted\":\"17 ₽\",\"size\":\"15\",\"size_formatted\":\"15 г\"}],\"price\":\"170000\",\"price_formatted\":\"17 ₽\",\"photo\":\"https:\\/\\/cdn.foodpicasso.com\\/assets\\/2022\\/07\\/26\\/6ffb36fd8791beee98410f7d04fce6f5---jpg_160x160_b3903_convert.jpg\",\"photoPart\":\"https:\\/\\/cdn.foodpicasso.com\\/assets\\/2022\\/07\\/26\\/6ffb36fd8791beee98410f7d04fce6f5---jpg_375x375:whitepadding15_9edf7_convert.jpg\",\"size\":\"15\",\"size_formatted\":\"15 г\",\"min\":0,\"max\":0},{\"id\":14,\"name\":\"Горчица\",\"prices\":[{\"price\":\"100000\",\"price_formatted\":\"10 ₽\"}],\"price\":\"100000\",\"price_formatted\":\"10 ₽\",\"photo\":\"https:\\/\\/cdn.foodpicasso.com\\/assets\\/2022\\/07\\/26\\/d47473bd814449044c0dcf34983c9040---png_160x160_b3903_convert.png\",\"photoPart\":\"https:\\/\\/cdn.foodpicasso.com\\/assets\\/2022\\/07\\/26\\/d47473bd814449044c0dcf34983c9040---png_375x375:whitepadding15_9edf7_convert.png\",\"size\":\"\",\"size_formatted\":\"\",\"min\":0,\"max\":0},{\"id\":15,\"name\":\"Яйцо\",\"prices\":[{\"price\":\"250000\",\"price_formatted\":\"25 ₽\",\"size\":\"20\",\"size_formatted\":\"20 г\"}],\"price\":\"250000\",\"price_formatted\":\"25 ₽\",\"photo\":\"https:\\/\\/cdn.foodpicasso.com\\/assets\\/2022\\/07\\/26\\/592fe930494dd2d25e5756e72a3b0d2f---jpg_160x160_b3903_convert.jpg\",\"photoPart\":\"https:\\/\\/cdn.foodpicasso.com\\/assets\\/2022\\/07\\/26\\/592fe930494dd2d25e5756e72a3b0d2f---jpg_375x375:whitepadding15_9edf7_convert.jpg\",\"size\":\"20\",\"size_formatted\":\"20 г\",\"min\":0,\"max\":0},{\"id\":93,\"name\":\"Рубленый бифштекс из говядины\",\"prices\":[{\"price\":\"730000\",\"price_formatted\":\"73 ₽\",\"size\":\"80\",\"size_formatted\":\"80 г\"}],\"price\":\"730000\",\"price_formatted\":\"73 ₽\",\"photo\":\"https:\\/\\/cdn.foodpicasso.com\\/assets\\/2022\\/07\\/27\\/cd8bab043d870f9b582393d1bcf8c502---jpg_160x160_b3903_convert.jpg\",\"photoPart\":\"https:\\/\\/cdn.foodpicasso.com\\/assets\\/2022\\/07\\/27\\/cd8bab043d870f9b582393d1bcf8c502---jpg_375x375:whitepadding15_9edf7_convert.jpg\",\"size\":\"80\",\"size_formatted\":\"80 г\",\"min\":0,\"max\":0},{\"id\":94,\"name\":\"Куриное филе в панировке\",\"prices\":[{\"price\":\"550000\",\"price_formatted\":\"55 ₽\",\"size\":\"80\",\"size_formatted\":\"80 г\"}],\"price\":\"550000\",\"price_formatted\":\"55 ₽\",\"photo\":\"https:\\/\\/cdn.foodpicasso.com\\/assets\\/2022\\/07\\/27\\/47e053e1ee0cdce8889d017874467726---jpg_160x160_b3903_convert.jpg\",\"photoPart\":\"https:\\/\\/cdn.foodpicasso.com\\/assets\\/2022\\/07\\/27\\/47e053e1ee0cdce8889d017874467726---jpg_375x375:whitepadding15_9edf7_convert.jpg\",\"size\":\"80\",\"size_formatted\":\"80 г\",\"min\":0,\"max\":0},{\"id\":95,\"name\":\"Лист салата\",\"prices\":[{\"price\":\"100000\",\"price_formatted\":\"10 ₽\",\"size\":\"10\",\"size_formatted\":\"10 г\"}],\"price\":\"100000\",\"price_formatted\":\"10 ₽\",\"photo\":\"https:\\/\\/cdn.foodpicasso.com\\/assets\\/2022\\/07\\/27\\/89184e3f5ac28a020a528552b2675b40---jpg_160x160_b3903_convert.jpg\",\"photoPart\":\"https:\\/\\/cdn.foodpicasso.com\\/assets\\/2022\\/07\\/27\\/89184e3f5ac28a020a528552b2675b40---jpg_375x375:whitepadding15_9edf7_convert.jpg\",\"size\":\"10\",\"size_formatted\":\"10 г\",\"min\":0,\"max\":0},{\"id\":96,\"name\":\"Фри\",\"prices\":[{\"price\":\"380000\",\"price_formatted\":\"38 ₽\",\"size\":\"75\",\"size_formatted\":\"75 г\"}],\"price\":\"380000\",\"price_formatted\":\"38 ₽\",\"photo\":\"https:\\/\\/cdn.foodpicasso.com\\/assets\\/2022\\/07\\/27\\/11ac767ce3f35ee9a208a2ea1b132580---jpeg_160x160_b3903_convert.jpeg\",\"photoPart\":\"https:\\/\\/cdn.foodpicasso.com\\/assets\\/2022\\/07\\/27\\/11ac767ce3f35ee9a208a2ea1b132580---jpeg_375x375:whitepadding15_9edf7_convert.jpeg\",\"size\":\"75\",\"size_formatted\":\"75 г\",\"min\":0,\"max\":0}],\"quarterType\":\"\",\"min\":0,\"max\":0},{\"title\":\"Сделай вкуснее\",\"type\":\"many_many\",\"required\":true,\"custom\":false,\"options\":[{\"id\":47,\"name\":\"Маринованный лучок\",\"prices\":[{\"price\":0,\"price_formatted\":\"0 ₽\"}],\"price\":0,\"price_formatted\":\"0 ₽\",\"photo\":\"https:\\/\\/cdn.foodpicasso.com\\/assets\\/2022\\/07\\/26\\/4fcd48fe7acb9ff3ba358d215562f8c3---jpg_160x160_b3903_convert.jpg\",\"photoPart\":\"https:\\/\\/cdn.foodpicasso.com\\/assets\\/2022\\/07\\/26\\/4fcd48fe7acb9ff3ba358d215562f8c3---jpg_375x375:whitepadding15_9edf7_convert.jpg\",\"size\":\"\",\"size_formatted\":\"\",\"min\":0,\"max\":0},{\"id\":48,\"name\":\"Горчица\",\"prices\":[{\"price\":0,\"price_formatted\":\"0 ₽\"}],\"price\":0,\"price_formatted\":\"0 ₽\",\"photo\":\"https:\\/\\/cdn.foodpicasso.com\\/assets\\/2022\\/07\\/26\\/9c74acfe562dab9859eddc026f9b4619---png_160x160_b3903_convert.png\",\"photoPart\":\"https:\\/\\/cdn.foodpicasso.com\\/assets\\/2022\\/07\\/26\\/9c74acfe562dab9859eddc026f9b4619---png_375x375:whitepadding15_9edf7_convert.png\",\"size\":\"\",\"size_formatted\":\"\",\"min\":0,\"max\":0},{\"id\":127,\"name\":\"Без лука\",\"prices\":[{\"price\":0,\"price_formatted\":\"0 ₽\"}],\"price\":0,\"price_formatted\":\"0 ₽\",\"photo\":\"https:\\/\\/cdn.foodpicasso.com\\/assets\\/2022\\/07\\/26\\/ffc79de2a3b4372f4db880060cb3713a---jpg_160x160_b3903_convert.jpg\",\"photoPart\":\"https:\\/\\/cdn.foodpicasso.com\\/assets\\/2022\\/07\\/26\\/ffc79de2a3b4372f4db880060cb3713a---jpg_375x375:whitepadding15_9edf7_convert.jpg\",\"size\":\"\",\"size_formatted\":\"\",\"min\":0,\"max\":0},{\"id\":128,\"name\":\"Без горчицы\",\"prices\":[{\"price\":0,\"price_formatted\":\"0 ₽\"}],\"price\":0,\"price_formatted\":\"0 ₽\",\"photo\":\"https:\\/\\/cdn.foodpicasso.com\\/assets\\/2022\\/07\\/26\\/01cfe1883bb4409a76de5c7b3e341cde---jpg_160x160_b3903_convert.jpg\",\"photoPart\":\"https:\\/\\/cdn.foodpicasso.com\\/assets\\/2022\\/07\\/26\\/01cfe1883bb4409a76de5c7b3e341cde---jpg_375x375:whitepadding15_9edf7_convert.jpg\",\"size\":\"\",\"size_formatted\":\"\",\"min\":0,\"max\":0}],\"quarterType\":\"\",\"min\":0,\"max\":0}]",
	"Хот-доги": "[{\"title\":\"Добавки\",\"type\":\"many_many\",\"required\":false,\"custom\":false,\"options\":[{\"id\":2,\"name\":\"Маринованный огурчик\",\"prices\":[{\"price\":\"250000\",\"price_formatted\":\"25 ₽\",\"size\":\"40\",\"size_formatted\":\"40 г\"}],\"price\":\"250000\",\"price_formatted\":\"25 ₽\",\"photo\":\"https:\\/\\/cdn.foodpicasso.com\\/assets\\/2022\\/07\\/26\\/3027c57c6ff755a36a23f7279b0a9630---jpg_160x160_b3903_convert.jpg\",\"photoPart\":\"https:\\/\\/cdn.foodpicasso.com\\/assets\\/2022\\/07\\/26\\/3027c57c6ff755a36a23f7279b0a9630---jpg_375x375:whitepadding15_9edf7_convert.jpg\",\"size\":\"40\",\"size_formatted\":\"40 г\",\"min\":0,\"max\":0},{\"id\":3,\"name\":\"Свежий огурчик\",\"prices\":[{\"price\":\"230000\",\"price_formatted\":\"23 ₽\",\"size\":\"40\",\"size_formatted\":\"40 г\"}],\"price\":\"230000\",\"price_formatted\":\"23 ₽\",\"photo\":\"https:\\/\\/cdn.foodpicasso.com\\/assets\\/2022\\/07\\/26\\/f31b632903ee3d0e6249289f618eb247---png_160x160_b3903_convert.png\",\"photoPart\":\"https:\\/\\/cdn.foodpicasso.com\\/assets\\/2022\\/07\\/26\\/f31b632903ee3d0e6249289f618eb247---png_375x375:whitepadding15_9edf7_convert.png\",\"size\":\"40\",\"size_formatted\":\"40 г\",\"min\":0,\"max\":0},{\"id\":4,\"name\":\"Лучок маринованный\",\"prices\":[{\"price\":\"100000\",\"price_formatted\":\"10 ₽\",\"size\":\"15\",\"size_formatted\":\"15 г\"}],\"price\":\"100000\",\"price_formatted\":\"10 ₽\",\"photo\":\"https:\\/\\/cdn.foodpicasso.com\\/assets\\/2022\\/07\\/26\\/6d1aab5de9b6f247f9afac3ee819846d---jpg_160x160_b3903_convert.jpg\",\"photoPart\":\"https:\\/\\/cdn.foodpicasso.com\\/assets\\/2022\\/07\\/26\\/6d1aab5de9b6f247f9afac3ee819846d---jpg_375x375:whitepadding15_9edf7_convert.jpg\",\"size\":\"15\",\"size_formatted\":\"15 г\",\"min\":0,\"max\":0},{\"id\":6,\"name\":\"Грибочки маринованные\",\"prices\":[{\"price\":\"770000\",\"price_formatted\":\"77 ₽\",\"size\":\"40\",\"size_formatted\":\"40 г\"}],\"price\":\"770000\",\"price_formatted\":\"77 ₽\",\"photo\":\"https:\\/\\/cdn.foodpicasso.com\\/assets\\/2022\\/07\\/26\\/5242c27b01fd320ea21196c89f7f4e39---jpg_160x160_b3903_convert.jpg\",\"photoPart\":\"https:\\/\\/cdn.foodpicasso.com\\/assets\\/2022\\/07\\/26\\/5242c27b01fd320ea21196c89f7f4e39---jpg_375x375:whitepadding15_9edf7_convert.jpg\",\"size\":\"40\",\"size_formatted\":\"40 г\",\"min\":0,\"max\":0},{\"id\":7,\"name\":\"Перчик болгарский\",\"prices\":[{\"price\":\"350000\",\"price_formatted\":\"35 ₽\",\"size\":\"15\",\"size_formatted\":\"15 г\"}],\"price\":\"350000\",\"price_formatted\":\"35 ₽\",\"photo\":\"https:\\/\\/cdn.foodpicasso.com\\/assets\\/2022\\/07\\/26\\/e024751115d70ea661433d0d73c1a659---jpg_160x160_b3903_convert.jpg\",\"photoPart\":\"https:\\/\\/cdn.foodpicasso.com\\/assets\\/2022\\/07\\/26\\/e024751115d70ea661433d0d73c1a659---jpg_375x375:whitepadding15_9edf7_convert.jpg\",\"size\":\"15\",\"size_formatted\":\"15 г\",\"min\":0,\"max\":0},{\"id\":9,\"name\":\"Томат\",\"prices\":[{\"price\":\"250000\",\"price_formatted\":\"25 ₽\",\"size\":\"40\",\"size_formatted\":\"40 г\"}],\"price\":\"250000\",\"price_formatted\":\"25 ₽\",\"photo\":\"https:\\/\\/cdn.foodpicasso.com\\/assets\\/2022\\/07\\/26\\/c7a108c28e3bb41dac5a8549386f89b5---jpeg_160x160_b3903_convert.jpeg\",\"photoPart\":\"https:\\/\\/cdn.foodpicasso.com\\/assets\\/2022\\/07\\/26\\/c7a108c28e3bb41dac5a8549386f89b5---jpeg_375x375:whitepadding15_9edf7_convert.jpeg\",\"size\":\"40\",\"size_formatted\":\"40 г\",\"min\":0,\"max\":0},{\"id\":11,\"name\":\"Бекон\",\"prices\":[{\"price\":\"730000\",\"price_formatted\":\"73 ₽\",\"size\":\"40\",\"size_formatted\":\"40 г\"}],\"price\":\"730000\",\"price_formatted\":\"73 ₽\",\"photo\":\"https:\\/\\/cdn.foodpicasso.com\\/assets\\/2022\\/07\\/26\\/f5be1451d119eb263739e675853d89c4---jpeg_160x160_b3903_convert.jpeg\",\"photoPart\":\"https:\\/\\/cdn.foodpicasso.com\\/assets\\/2022\\/07\\/26\\/f5be1451d119eb263739e675853d89c4---jpeg_375x375:whitepadding15_9edf7_convert.jpeg\",\"size\":\"40\",\"size_formatted\":\"40 г\",\"min\":0,\"max\":0},{\"id\":12,\"name\":\"Оливки\",\"prices\":[{\"price\":\"370000\",\"price_formatted\":\"37 ₽\",\"size\":\"15\",\"size_formatted\":\"15 г\"}],\"price\":\"370000\",\"price_formatted\":\"37 ₽\",\"photo\":\"https:\\/\\/cdn.foodpicasso.com\\/assets\\/2022\\/07\\/26\\/9e2c97a6a624aa46a29c914b8ddff5a2---jpg_160x160_b3903_convert.jpg\",\"photoPart\":\"https:\\/\\/cdn.foodpicasso.com\\/assets\\/2022\\/07\\/26\\/9e2c97a6a624aa46a29c914b8ddff5a2---jpg_375x375:whitepadding15_9edf7_convert.jpg\",\"size\":\"15\",\"size_formatted\":\"15 г\",\"min\":0,\"max\":0},{\"id\":13,\"name\":\"Сыр\",\"prices\":[{\"price\":\"170000\",\"price_formatted\":\"17 ₽\",\"size\":\"15\",\"size_formatted\":\"15 г\"}],\"price\":\"170000\",\"price_formatted\":\"17 ₽\",\"photo\":\"https:\\/\\/cdn.foodpicasso.com\\/assets\\/2022\\/07\\/26\\/6ffb36fd8791beee98410f7d04fce6f5---jpg_160x160_b3903_convert.jpg\",\"photoPart\":\"https:\\/\\/cdn.foodpicasso.com\\/assets\\/2022\\/07\\/26\\/6ffb36fd8791beee98410f7d04fce6f5---jpg_375x375:whitepadding15_9edf7_convert.jpg\",\"size\":\"15\",\"size_formatted\":\"15 г\",\"min\":0,\"max\":0},{\"id\":14,\"name\":\"Горчица\",\"prices\":[{\"price\":\"100000\",\"price_formatted\":\"10 ₽\"}],\"price\":\"100000\",\"price_formatted\":\"10 ₽\",\"photo\":\"https:\\/\\/cdn.foodpicasso.com\\/assets\\/2022\\/07\\/26\\/d47473bd814449044c0dcf34983c9040---png_160x160_b3903_convert.png\",\"photoPart\":\"https:\\/\\/cdn.foodpicasso.com\\/assets\\/2022\\/07\\/26\\/d47473bd814449044c0dcf34983c9040---png_375x375:whitepadding15_9edf7_convert.png\",\"size\":\"\",\"size_formatted\":\"\",\"min\":0,\"max\":0},{\"id\":95,\"name\":\"Лист салата\",\"prices\":[{\"price\":\"100000\",\"price_formatted\":\"10 ₽\",\"size\":\"10\",\"size_formatted\":\"10 г\"}],\"price\":\"100000\",\"price_formatted\":\"10 ₽\",\"photo\":\"https:\\/\\/cdn.foodpicasso.com\\/assets\\/2022\\/07\\/27\\/89184e3f5ac28a020a528552b2675b40---jpg_160x160_b3903_convert.jpg\",\"photoPart\":\"https:\\/\\/cdn.foodpicasso.com\\/assets\\/2022\\/07\\/27\\/89184e3f5ac28a020a528552b2675b40---jpg_375x375:whitepadding15_9edf7_convert.jpg\",\"size\":\"10\",\"size_formatted\":\"10 г\",\"min\":0,\"max\":0},{\"id\":96,\"name\":\"Фри\",\"prices\":[{\"price\":\"380000\",\"price_formatted\":\"38 ₽\",\"size\":\"75\",\"size_formatted\":\"75 г\"}],\"price\":\"380000\",\"price_formatted\":\"38 ₽\",\"photo\":\"https:\\/\\/cdn.foodpicasso.com\\/assets\\/2022\\/07\\/27\\/11ac767ce3f35ee9a208a2ea1b132580---jpeg_160x160_b3903_convert.jpeg\",\"photoPart\":\"https:\\/\\/cdn.foodpicasso.com\\/assets\\/2022\\/07\\/27\\/11ac767ce3f35ee9a208a2ea1b132580---jpeg_375x375:whitepadding15_9edf7_convert.jpeg\",\"size\":\"75\",\"size_formatted\":\"75 г\",\"min\":0,\"max\":0}],\"quarterType\":\"\",\"min\":0,\"max\":0},{\"title\":\"Сделай вкуснее\",\"type\":\"many_many\",\"required\":true,\"custom\":false,\"options\":[{\"id\":47,\"name\":\"Маринованный лучок\",\"prices\":[{\"price\":0,\"price_formatted\":\"0 ₽\"}],\"price\":0,\"price_formatted\":\"0 ₽\",\"photo\":\"https:\\/\\/cdn.foodpicasso.com\\/assets\\/2022\\/07\\/26\\/4fcd48fe7acb9ff3ba358d215562f8c3---jpg_160x160_b3903_convert.jpg\",\"photoPart\":\"https:\\/\\/cdn.foodpicasso.com\\/assets\\/2022\\/07\\/26\\/4fcd48fe7acb9ff3ba358d215562f8c3---jpg_375x375:whitepadding15_9edf7_convert.jpg\",\"size\":\"\",\"size_formatted\":\"\",\"min\":0,\"max\":0},{\"id\":48,\"name\":\"Горчица\",\"prices\":[{\"price\":0,\"price_formatted\":\"0 ₽\"}],\"price\":0,\"price_formatted\":\"0 ₽\",\"photo\":\"https:\\/\\/cdn.foodpicasso.com\\/assets\\/2022\\/07\\/26\\/9c74acfe562dab9859eddc026f9b4619---png_160x160_b3903_convert.png\",\"photoPart\":\"https:\\/\\/cdn.foodpicasso.com\\/assets\\/2022\\/07\\/26\\/9c74acfe562dab9859eddc026f9b4619---png_375x375:whitepadding15_9edf7_convert.png\",\"size\":\"\",\"size_formatted\":\"\",\"min\":0,\"max\":0},{\"id\":127,\"name\":\"Без лука\",\"prices\":[{\"price\":0,\"price_formatted\":\"0 ₽\"}],\"price\":0,\"price_formatted\":\"0 ₽\",\"photo\":\"https:\\/\\/cdn.foodpicasso.com\\/assets\\/2022\\/07\\/26\\/ffc79de2a3b4372f4db880060cb3713a---jpg_160x160_b3903_convert.jpg\",\"photoPart\":\"https:\\/\\/cdn.foodpicasso.com\\/assets\\/2022\\/07\\/26\\/ffc79de2a3b4372f4db880060cb3713a---jpg_375x375:whitepadding15_9edf7_convert.jpg\",\"size\":\"\",\"size_formatted\":\"\",\"min\":0,\"max\":0},{\"id\":128,\"name\":\"Без горчицы\",\"prices\":[{\"price\":0,\"price_formatted\":\"0 ₽\"}],\"price\":0,\"price_formatted\":\"0 ₽\",\"photo\":\"https:\\/\\/cdn.foodpicasso.com\\/assets\\/2022\\/07\\/26\\/01cfe1883bb4409a76de5c7b3e341cde---jpg_160x160_b3903_convert.jpg\",\"photoPart\":\"https:\\/\\/cdn.foodpicasso.com\\/assets\\/2022\\/07\\/26\\/01cfe1883bb4409a76de5c7b3e341cde---jpg_375x375:whitepadding15_9edf7_convert.jpg\",\"size\":\"\",\"size_formatted\":\"\",\"min\":0,\"max\":0}],\"quarterType\":\"\",\"min\":0,\"max\":0}]",
	"Крылья и ножки": "[{\"title\":\"Соусы\",\"type\":\"many_many\",\"required\":false,\"custom\":false,\"options\":[{\"id\":132,\"name\":\"Без соуса\",\"prices\":[{\"price\":0,\"price_formatted\":\"0 ₽\"}],\"price\":0,\"price_formatted\":\"0 ₽\",\"photo\":\"https:\\/\\/cdn.foodpicasso.com\\/assets\\/2022\\/07\\/26\\/04d2913ea263586c8509e46b847afeea---jpg_160x160_b3903_convert.jpg\",\"photoPart\":\"https:\\/\\/cdn.foodpicasso.com\\/assets\\/2022\\/07\\/26\\/04d2913ea263586c8509e46b847afeea---jpg_375x375:whitepadding15_9edf7_convert.jpg\",\"size\":\"\",\"size_formatted\":\"\",\"min\":0,\"max\":0},{\"id\":49,\"name\":\"Томатный кетчуп\",\"prices\":[{\"price\":\"260000\",\"price_formatted\":\"26 ₽\",\"size\":\"40\",\"size_formatted\":\"40 г\"}],\"price\":\"260000\",\"price_formatted\":\"26 ₽\",\"photo\":\"https:\\/\\/cdn.foodpicasso.com\\/assets\\/2022\\/07\\/26\\/601e403d7e68b5ad04e69dce1417531c---jpg_160x160_b3903_convert.jpg\",\"photoPart\":\"https:\\/\\/cdn.foodpicasso.com\\/assets\\/2022\\/07\\/26\\/601e403d7e68b5ad04e69dce1417531c---jpg_375x375:whitepadding15_9edf7_convert.jpg\",\"size\":\"40\",\"size_formatted\":\"40 г\",\"min\":0,\"max\":0},{\"id\":50,\"name\":\"Соус Чили\",\"prices\":[{\"price\":\"430000\",\"price_formatted\":\"43 ₽\",\"size\":\"40\",\"size_formatted\":\"40 г\"}],\"price\":\"430000\",\"price_formatted\":\"43 ₽\",\"photo\":\"https:\\/\\/cdn.foodpicasso.com\\/assets\\/2022\\/07\\/26\\/eef4285ac6e066ab335d70dc2f5b77ee---png_160x160_b3903_convert.png\",\"photoPart\":\"https:\\/\\/cdn.foodpicasso.com\\/assets\\/2022\\/07\\/26\\/eef4285ac6e066ab335d70dc2f5b77ee---png_375x375:whitepadding15_9edf7_convert.png\",\"size\":\"40\",\"size_formatted\":\"40 г\",\"min\":0,\"max\":0},{\"id\":51,\"name\":\"Тайский соус\",\"prices\":[{\"price\":\"520000\",\"price_formatted\":\"52 ₽\",\"size\":\"40\",\"size_formatted\":\"40 г\"}],\"price\":\"520000\",\"price_formatted\":\"52 ₽\",\"photo\":\"https:\\/\\/cdn.foodpicasso.com\\/assets\\/2022\\/07\\/26\\/6a2e0699ef258c25dfa062aadc6c90dc---jpg_160x160_b3903_convert.jpg\",\"photoPart\":\"https:\\/\\/cdn.foodpicasso.com\\/assets\\/2022\\/07\\/26\\/6a2e0699ef258c25dfa062aadc6c90dc---jpg_375x375:whitepadding15_9edf7_convert.jpg\",\"size\":\"40\",\"size_formatted\":\"40 г\",\"min\":0,\"max\":0},{\"id\":52,\"name\":\"Фирменный соус\",\"prices\":[{\"price\":\"200000\",\"price_formatted\":\"20 ₽\",\"size\":\"40\",\"size_formatted\":\"40 г\"}],\"price\":\"200000\",\"price_formatted\":\"20 ₽\",\"photo\":\"https:\\/\\/cdn.foodpicasso.com\\/assets\\/2022\\/07\\/26\\/fc667b4ca67a4128810d147f84afde36---jpg_160x160_b3903_convert.jpg\",\"photoPart\":\"https:\\/\\/cdn.foodpicasso.com\\/assets\\/2022\\/07\\/26\\/fc667b4ca67a4128810d147f84afde36---jpg_375x375:whitepadding15_9edf7_convert.jpg\",\"size\":\"40\",\"size_formatted\":\"40 г\",\"min\":0,\"max\":0},{\"id\":53,\"name\":\"Сырный соус\",\"prices\":[{\"price\":\"440000\",\"price_formatted\":\"44 ₽\",\"size\":\"40\",\"size_formatted\":\"40 г\"}],\"price\":\"440000\",\"price_formatted\":\"44 ₽\",\"photo\":\"https:\\/\\/cdn.foodpicasso.com\\/assets\\/2022\\/07\\/26\\/715265820b430c651910f6304c86642c---jpg_160x160_b3903_convert.jpg\",\"photoPart\":\"https:\\/\\/cdn.foodpicasso.com\\/assets\\/2022\\/07\\/26\\/715265820b430c651910f6304c86642c---jpg_375x375:whitepadding15_9edf7_convert.jpg\",\"size\":\"40\",\"size_formatted\":\"40 г\",\"min\":0,\"max\":0},{\"id\":54,\"name\":\"Барбекю по-техасски\",\"prices\":[{\"price\":\"500000\",\"price_formatted\":\"50 ₽\",\"size\":\"40\",\"size_formatted\":\"40 г\"}],\"price\":\"500000\",\"price_formatted\":\"50 ₽\",\"photo\":\"https:\\/\\/cdn.foodpicasso.com\\/assets\\/2022\\/07\\/26\\/42dfc0ce7d54d72c62f16fcc95926894---jpg_160x160_b3903_convert.jpg\",\"photoPart\":\"https:\\/\\/cdn.foodpicasso.com\\/assets\\/2022\\/07\\/26\\/42dfc0ce7d54d72c62f16fcc95926894---jpg_375x375:whitepadding15_9edf7_convert.jpg\",\"size\":\"40\",\"size_formatted\":\"40 г\",\"min\":0,\"max\":0}],\"quarterType\":\"\",\"min\":0,\"max\":0}]",
	"Ланч": "[{\"title\":\"Добавки\",\"type\":\"many_many\",\"required\":false,\"custom\":false,\"options\":[{\"id\":2,\"name\":\"Маринованный огурчик\",\"prices\":[{\"price\":\"250000\",\"price_formatted\":\"25 ₽\",\"size\":\"40\",\"size_formatted\":\"40 г\"}],\"price\":\"250000\",\"price_formatted\":\"25 ₽\",\"photo\":\"https:\\/\\/cdn.foodpicasso.com\\/assets\\/2022\\/07\\/26\\/3027c57c6ff755a36a23f7279b0a9630---jpg_160x160_b3903_convert.jpg\",\"photoPart\":\"https:\\/\\/cdn.foodpicasso.com\\/assets\\/2022\\/07\\/26\\/3027c57c6ff755a36a23f7279b0a9630---jpg_375x375:whitepadding15_9edf7_convert.jpg\",\"size\":\"40\",\"size_formatted\":\"40 г\",\"min\":0,\"max\":0},{\"id\":3,\"name\":\"Свежий огурчик\",\"prices\":[{\"price\":\"230000\",\"price_formatted\":\"23 ₽\",\"size\":\"40\",\"size_formatted\":\"40 г\"}],\"price\":\"230000\",\"price_formatted\":\"23 ₽\",\"photo\":\"https:\\/\\/cdn.foodpicasso.com\\/assets\\/2022\\/07\\/26\\/f31b632903ee3d0e6249289f618eb247---png_160x160_b3903_convert.png\",\"photoPart\":\"https:\\/\\/cdn.foodpicasso.com\\/assets\\/2022\\/07\\/26\\/f31b632903ee3d0e6249289f618eb247---png_375x375:whitepadding15_9edf7_convert.png\",\"size\":\"40\",\"size_formatted\":\"40 г\",\"min\":0,\"max\":0},{\"id\":4,\"name\":\"Лучок маринованный\",\"prices\":[{\"price\":\"100000\",\"price_formatted\":\"10 ₽\",\"size\":\"15\",\"size_formatted\":\"15 г\"}],\"price\":\"100000\",\"price_formatted\":\"10 ₽\",\"photo\":\"https:\\/\\/cdn.foodpicasso.com\\/assets\\/2022\\/07\\/26\\/6d1aab5de9b6f247f9afac3ee819846d---jpg_160x160_b3903_convert.jpg\",\"photoPart\":\"https:\\/\\/cdn.foodpicasso.com\\/assets\\/2022\\/07\\/26\\/6d1aab5de9b6f247f9afac3ee819846d---jpg_375x375:whitepadding15_9edf7_convert.jpg\",\"size\":\"15\",\"size_formatted\":\"15 г\",\"min\":0,\"max\":0},{\"id\":6,\"name\":\"Грибочки маринованные\",\"prices\":[{\"price\":\"770000\",\"price_formatted\":\"77 ₽\",\"size\":\"40\",\"size_formatted\":\"40 г\"}],\"price\":\"770000\",\"price_formatted\":\"77 ₽\",\"photo\":\"https:\\/\\/cdn.foodpicasso.com\\/assets\\/2022\\/07\\/26\\/5242c27b01fd320ea21196c89f7f4e39---jpg_160x160_b3903_convert.jpg\",\"photoPart\":\"https:\\/\\/cdn.foodpicasso.com\\/assets\\/2022\\/07\\/26\\/5242c27b01fd320ea21196c89f7f4e39---jpg_375x375:whitepadding15_9edf7_convert.jpg\",\"size\":\"40\",\"size_formatted\":\"40 г\",\"min\":0,\"max\":0},{\"id\":7,\"name\":\"Перчик болгарский\",\"prices\":[{\"price\":\"350000\",\"price_formatted\":\"35 ₽\",\"size\":\"15\",\"size_formatted\":\"15 г\"}],\"price\":\"350000\",\"price_formatted\":\"35 ₽\",\"photo\":\"https:\\/\\/cdn.foodpicasso.com\\/assets\\/2022\\/07\\/26\\/e024751115d70ea661433d0d73c1a659---jpg_160x160_b3903_convert.jpg\",\"photoPart\":\"https:\\/\\/cdn.foodpicasso.com\\/assets\\/2022\\/07\\/26\\/e024751115d70ea661433d0d73c1a659---jpg_375x375:whitepadding15_9edf7_convert.jpg\",\"size\":\"15\",\"size_formatted\":\"15 г\",\"min\":0,\"max\":0},{\"id\":9,\"name\":\"Томат\",\"prices\":[{\"price\":\"250000\",\"price_formatted\":\"25 ₽\",\"size\":\"40\",\"size_formatted\":\"40 г\"}],\"price\":\"250000\",\"price_formatted\":\"25 ₽\",\"photo\":\"https:\\/\\/cdn.foodpicasso.com\\/assets\\/2022\\/07\\/26\\/c7a108c28e3bb41dac5a8549386f89b5---jpeg_160x160_b3903_convert.jpeg\",\"photoPart\":\"https:\\/\\/cdn.foodpicasso.com\\/assets\\/2022\\/07\\/26\\/c7a108c28e3bb41dac5a8549386f89b5---jpeg_375x375:whitepadding15_9edf7_convert.jpeg\",\"size\":\"40\",\"size_formatted\":\"40 г\",\"min\":0,\"max\":0},{\"id\":11,\"name\":\"Бекон\",\"prices\":[{\"price\":\"730000\",\"price_formatted\":\"73 ₽\",\"size\":\"40\",\"size_formatted\":\"40 г\"}],\"price\":\"730000\",\"price_formatted\":\"73 ₽\",\"photo\":\"https:\\/\\/cdn.foodpicasso.com\\/assets\\/2022\\/07\\/26\\/f5be1451d119eb263739e675853d89c4---jpeg_160x160_b3903_convert.jpeg\",\"photoPart\":\"https:\\/\\/cdn.foodpicasso.com\\/assets\\/2022\\/07\\/26\\/f5be1451d119eb263739e675853d89c4---jpeg_375x375:whitepadding15_9edf7_convert.jpeg\",\"size\":\"40\",\"size_formatted\":\"40 г\",\"min\":0,\"max\":0},{\"id\":12,\"name\":\"Оливки\",\"prices\":[{\"price\":\"370000\",\"price_formatted\":\"37 ₽\",\"size\":\"15\",\"size_formatted\":\"15 г\"}],\"price\":\"370000\",\"price_formatted\":\"37 ₽\",\"photo\":\"https:\\/\\/cdn.foodpicasso.com\\/assets\\/2022\\/07\\/26\\/9e2c97a6a624aa46a29c914b8ddff5a2---jpg_160x160_b3903_convert.jpg\",\"photoPart\":\"https:\\/\\/cdn.foodpicasso.com\\/assets\\/2022\\/07\\/26\\/9e2c97a6a624aa46a29c914b8ddff5a2---jpg_375x375:whitepadding15_9edf7_convert.jpg\",\"size\":\"15\",\"size_formatted\":\"15 г\",\"min\":0,\"max\":0},{\"id\":13,\"name\":\"Сыр\",\"prices\":[{\"price\":\"170000\",\"price_formatted\":\"17 ₽\",\"size\":\"15\",\"size_formatted\":\"15 г\"}],\"price\":\"170000\",\"price_formatted\":\"17 ₽\",\"photo\":\"https:\\/\\/cdn.foodpicasso.com\\/assets\\/2022\\/07\\/26\\/6ffb36fd8791beee98410f7d04fce6f5---jpg_160x160_b3903_convert.jpg\",\"photoPart\":\"https:\\/\\/cdn.foodpicasso.com\\/assets\\/2022\\/07\\/26\\/6ffb36fd8791beee98410f7d04fce6f5---jpg_375x375:whitepadding15_9edf7_convert.jpg\",\"size\":\"15\",\"size_formatted\":\"15 г\",\"min\":0,\"max\":0},{\"id\":14,\"name\":\"Горчица\",\"prices\":[{\"price\":\"100000\",\"price_formatted\":\"10 ₽\"}],\"price\":\"100000\",\"price_formatted\":\"10 ₽\",\"photo\":\"https:\\/\\/cdn.foodpicasso.com\\/assets\\/2022\\/07\\/26\\/d47473bd814449044c0dcf34983c9040---png_160x160_b3903_convert.png\",\"photoPart\":\"https:\\/\\/cdn.foodpicasso.com\\/assets\\/2022\\/07\\/26\\/d47473bd814449044c0dcf34983c9040---png_375x375:whitepadding15_9edf7_convert.png\",\"size\":\"\",\"size_formatted\":\"\",\"min\":0,\"max\":0},{\"id\":15,\"name\":\"Яйцо\",\"prices\":[{\"price\":\"250000\",\"price_formatted\":\"25 ₽\",\"size\":\"20\",\"size_formatted\":\"20 г\"}],\"price\":\"250000\",\"price_formatted\":\"25 ₽\",\"photo\":\"https:\\/\\/cdn.foodpicasso.com\\/assets\\/2022\\/07\\/26\\/592fe930494dd2d25e5756e72a3b0d2f---jpg_160x160_b3903_convert.jpg\",\"photoPart\":\"https:\\/\\/cdn.foodpicasso.com\\/assets\\/2022\\/07\\/26\\/592fe930494dd2d25e5756e72a3b0d2f---jpg_375x375:whitepadding15_9edf7_convert.jpg\",\"size\":\"20\",\"size_formatted\":\"20 г\",\"min\":0,\"max\":0},{\"id\":93,\"name\":\"Рубленый бифштекс из говядины\",\"prices\":[{\"price\":\"730000\",\"price_formatted\":\"73 ₽\",\"size\":\"80\",\"size_formatted\":\"80 г\"}],\"price\":\"730000\",\"price_formatted\":\"73 ₽\",\"photo\":\"https:\\/\\/cdn.foodpicasso.com\\/assets\\/2022\\/07\\/27\\/cd8bab043d870f9b582393d1bcf8c502---jpg_160x160_b3903_convert.jpg\",\"photoPart\":\"https:\\/\\/cdn.foodpicasso.com\\/assets\\/2022\\/07\\/27\\/cd8bab043d870f9b582393d1bcf8c502---jpg_375x375:whitepadding15_9edf7_convert.jpg\",\"size\":\"80\",\"size_formatted\":\"80 г\",\"min\":0,\"max\":0},{\"id\":94,\"name\":\"Куриное филе в панировке\",\"prices\":[{\"price\":\"550000\",\"price_formatted\":\"55 ₽\",\"size\":\"80\",\"size_formatted\":\"80 г\"}],\"price\":\"550000\",\"price_formatted\":\"55 ₽\",\"photo\":\"https:\\/\\/cdn.foodpicasso.com\\/assets\\/2022\\/07\\/27\\/47e053e1ee0cdce8889d017874467726---jpg_160x160_b3903_convert.jpg\",\"photoPart\":\"https:\\/\\/cdn.foodpicasso.com\\/assets\\/2022\\/07\\/27\\/47e053e1ee0cdce8889d017874467726---jpg_375x375:whitepadding15_9edf7_convert.jpg\",\"size\":\"80\",\"size_formatted\":\"80 г\",\"min\":0,\"max\":0},{\"id\":95,\"name\":\"Лист салата\",\"prices\":[{\"price\":\"100000\",\"price_formatted\":\"10 ₽\",\"size\":\"10\",\"size_formatted\":\"10 г\"}],\"price\":\"100000\",\"price_formatted\":\"10 ₽\",\"photo\":\"https:\\/\\/cdn.foodpicasso.com\\/assets\\/2022\\/07\\/27\\/89184e3f5ac28a020a528552b2675b40---jpg_160x160_b3903_convert.jpg\",\"photoPart\":\"https:\\/\\/cdn.foodpicasso.com\\/assets\\/2022\\/07\\/27\\/89184e3f5ac28a020a528552b2675b40---jpg_375x375:whitepadding15_9edf7_convert.jpg\",\"size\":\"10\",\"size_formatted\":\"10 г\",\"min\":0,\"max\":0},{\"id\":96,\"name\":\"Фри\",\"prices\":[{\"price\":\"380000\",\"price_formatted\":\"38 ₽\",\"size\":\"75\",\"size_formatted\":\"75 г\"}],\"price\":\"380000\",\"price_formatted\":\"38 ₽\",\"photo\":\"https:\\/\\/cdn.foodpicasso.com\\/assets\\/2022\\/07\\/27\\/11ac767ce3f35ee9a208a2ea1b132580---jpeg_160x160_b3903_convert.jpeg\",\"photoPart\":\"https:\\/\\/cdn.foodpicasso.com\\/assets\\/2022\\/07\\/27\\/11ac767ce3f35ee9a208a2ea1b132580---jpeg_375x375:whitepadding15_9edf7_convert.jpeg\",\"size\":\"75\",\"size_formatted\":\"75 г\",\"min\":0,\"max\":0}],\"quarterType\":\"\",\"min\":0,\"max\":0}]",
	"Картофель": "[{\"title\":\"Соусы\",\"type\":\"many_many\",\"required\":false,\"custom\":false,\"options\":[{\"id\":132,\"name\":\"Без соуса\",\"prices\":[{\"price\":0,\"price_formatted\":\"0 ₽\"}],\"price\":0,\"price_formatted\":\"0 ₽\",\"photo\":\"https:\\/\\/cdn.foodpicasso.com\\/assets\\/2022\\/07\\/26\\/04d2913ea263586c8509e46b847afeea---jpg_160x160_b3903_convert.jpg\",\"photoPart\":\"https:\\/\\/cdn.foodpicasso.com\\/assets\\/2022\\/07\\/26\\/04d2913ea263586c8509e46b847afeea---jpg_375x375:whitepadding15_9edf7_convert.jpg\",\"size\":\"\",\"size_formatted\":\"\",\"min\":0,\"max\":0},{\"id\":49,\"name\":\"Томатный кетчуп\",\"prices\":[{\"price\":\"260000\",\"price_formatted\":\"26 ₽\",\"size\":\"40\",\"size_formatted\":\"40 г\"}],\"price\":\"260000\",\"price_formatted\":\"26 ₽\",\"photo\":\"https:\\/\\/cdn.foodpicasso.com\\/assets\\/2022\\/07\\/26\\/601e403d7e68b5ad04e69dce1417531c---jpg_160x160_b3903_convert.jpg\",\"photoPart\":\"https:\\/\\/cdn.foodpicasso.com\\/assets\\/2022\\/07\\/26\\/601e403d7e68b5ad04e69dce1417531c---jpg_375x375:whitepadding15_9edf7_convert.jpg\",\"size\":\"40\",\"size_formatted\":\"40 г\",\"min\":0,\"max\":0},{\"id\":50,\"name\":\"Соус Чили\",\"prices\":[{\"price\":\"430000\",\"price_formatted\":\"43 ₽\",\"size\":\"40\",\"size_formatted\":\"40 г\"}],\"price\":\"430000\",\"price_formatted\":\"43 ₽\",\"photo\":\"https:\\/\\/cdn.foodpicasso.com\\/assets\\/2022\\/07\\/26\\/eef4285ac6e066ab335d70dc2f5b77ee---png_160x160_b3903_convert.png\",\"photoPart\":\"https:\\/\\/cdn.foodpicasso.com\\/assets\\/2022\\/07\\/26\\/eef4285ac6e066ab335d70dc2f5b77ee---png_375x375:whitepadding15_9edf7_convert.png\",\"size\":\"40\",\"size_formatted\":\"40 г\",\"min\":0,\"max\":0},{\"id\":51,\"name\":\"Тайский соус\",\"prices\":[{\"price\":\"520000\",\"price_formatted\":\"52 ₽\",\"size\":\"40\",\"size_formatted\":\"40 г\"}],\"price\":\"520000\",\"price_formatted\":\"52 ₽\",\"photo\":\"https:\\/\\/cdn.foodpicasso.com\\/assets\\/2022\\/07\\/26\\/6a2e0699ef258c25dfa062aadc6c90dc---jpg_160x160_b3903_convert.jpg\",\"photoPart\":\"https:\\/\\/cdn.foodpicasso.com\\/assets\\/2022\\/07\\/26\\/6a2e0699ef258c25dfa062aadc6c90dc---jpg_375x375:whitepadding15_9edf7_convert.jpg\",\"size\":\"40\",\"size_formatted\":\"40 г\",\"min\":0,\"max\":0},{\"id\":52,\"name\":\"Фирменный соус\",\"prices\":[{\"price\":\"200000\",\"price_formatted\":\"20 ₽\",\"size\":\"40\",\"size_formatted\":\"40 г\"}],\"price\":\"200000\",\"price_formatted\":\"20 ₽\",\"photo\":\"https:\\/\\/cdn.foodpicasso.com\\/assets\\/2022\\/07\\/26\\/fc667b4ca67a4128810d147f84afde36---jpg_160x160_b3903_convert.jpg\",\"photoPart\":\"https:\\/\\/cdn.foodpicasso.com\\/assets\\/2022\\/07\\/26\\/fc667b4ca67a4128810d147f84afde36---jpg_375x375:whitepadding15_9edf7_convert.jpg\",\"size\":\"40\",\"size_formatted\":\"40 г\",\"min\":0,\"max\":0},{\"id\":53,\"name\":\"Сырный соус\",\"prices\":[{\"price\":\"440000\",\"price_formatted\":\"44 ₽\",\"size\":\"40\",\"size_formatted\":\"40 г\"}],\"price\":\"440000\",\"price_formatted\":\"44 ₽\",\"photo\":\"https:\\/\\/cdn.foodpicasso.com\\/assets\\/2022\\/07\\/26\\/715265820b430c651910f6304c86642c---jpg_160x160_b3903_convert.jpg\",\"photoPart\":\"https:\\/\\/cdn.foodpicasso.com\\/assets\\/2022\\/07\\/26\\/715265820b430c651910f6304c86642c---jpg_375x375:whitepadding15_9edf7_convert.jpg\",\"size\":\"40\",\"size_formatted\":\"40 г\",\"min\":0,\"max\":0},{\"id\":54,\"name\":\"Барбекю по-техасски\",\"prices\":[{\"price\":\"500000\",\"price_formatted\":\"50 ₽\",\"size\":\"40\",\"size_formatted\":\"40 г\"}],\"price\":\"500000\",\"price_formatted\":\"50 ₽\",\"photo\":\"https:\\/\\/cdn.foodpicasso.com\\/assets\\/2022\\/07\\/26\\/42dfc0ce7d54d72c62f16fcc95926894---jpg_160x160_b3903_convert.jpg\",\"photoPart\":\"https:\\/\\/cdn.foodpicasso.com\\/assets\\/2022\\/07\\/26\\/42dfc0ce7d54d72c62f16fcc95926894---jpg_375x375:whitepadding15_9edf7_convert.jpg\",\"size\":\"40\",\"size_formatted\":\"40 г\",\"min\":0,\"max\":0}],\"quarterType\":\"\",\"min\":0,\"max\":0}]"
}
